kweathercord/__init__.py
kweathercord/client.py
kweathercord/enums.py
kweathercord/exception.py
kweathercord/model.py
kweathercord/utils.py
kweathercord/view.py
kweathercord/area/weather_area.json
kweathercord/asset/img/clear.png
kweathercord/asset/img/clear_night.png
kweathercord/asset/img/cloudy.png
kweathercord/asset/img/partly_cloudy.png
kweathercord/asset/img/partly_cloudy_night.png
kweathercord/asset/img/partly_snowy.png
kweathercord/asset/img/rain_with_snow.png
kweathercord/asset/img/rainy.png
kweathercord/asset/img/shower.png
kweathercord/asset/img/snowy.png
kweather_cord-0.1.3.dist-info/LICENSE
kweather_cord-0.1.3.dist-info/METADATA
kweather_cord-0.1.3.dist-info/WHEEL
kweather_cord-0.1.3.dist-info/top_level.txt
kweather_cord-0.1.3.dist-info/RECORD
