Metadata-Version: 2.1
Name: kweather-cord
Version: 0.1.3
Summary: Nice Embed Template for Korean Weather for Discord Bot
Author-email: Gooraeng <birdyoon1998@gmail.com>
License: MIT License
Project-URL: Repository, https://github.com/Gooraeng/KweatherDiscord
Keywords: koreaweather,kweather,공공데이터포털,기상청,discord,discord.py
Classifier: Development Status :: 5 - Production/Stable
Classifier: License :: OSI Approved :: MIT License
Classifier: Intended Audience :: Developers
Classifier: Natural Language :: Korean
Classifier: Programming Language :: Python :: 3.8
Classifier: Programming Language :: Python :: 3.9
Classifier: Programming Language :: Python :: 3.10
Classifier: Programming Language :: Python :: 3.11
Classifier: Programming Language :: Python :: 3.12
Classifier: Topic :: Internet
Classifier: Topic :: Software Development :: Libraries
Classifier: Topic :: Software Development :: Libraries :: Python Modules
Classifier: Topic :: Utilities
Classifier: Typing :: Typed
Requires-Python: >=3.8
License-File: LICENSE
Requires-Dist: discord.py >=2.4.0
Requires-Dist: rapidfuzz >=3.9
